FlexibleDate/FlexibleDate.py
FlexibleDate/requirements.txt
flexibledate-1.0.9.dist-info/licenses/LICENSE
flexibledate-1.0.9.dist-info/METADATA
flexibledate-1.0.9.dist-info/WHEEL
flexibledate-1.0.9.dist-info/top_level.txt
flexibledate-1.0.9.dist-info/RECORD
