Metadata-Version: 2.4
Name: FlexibleDate
Version: 1.0.9
Summary: This is a library used to make fuzzy date comparisons.
Home-page: https://github.com/byuawsfhtl/FlexibleDate.git
Author: Record Linking Lab
Author-email: recordlinkinglab@gmail.com
Project-URL: Bug Tracker, https://github.com/byuawsfhtl/FlexibleDate/issues
License-File: LICENSE
Requires-Dist: pydantic~=2.8.2
Requires-Dist: Unidecode~=1.3.8
Requires-Dist: python-dateutil~=2.9.0.post0
Requires-Dist: edtf~=5.0.0
Dynamic: author
Dynamic: author-email
Dynamic: description
Dynamic: description-content-type
Dynamic: home-page
Dynamic: license-file
Dynamic: project-url
Dynamic: requires-dist
Dynamic: summary
